convert/__init__.py
convert/convert_string.py
logging/__init__.py
logging/_debug.py
utils_lib-0.2.0.dev2022021300.dist-info/LICENSE
utils_lib-0.2.0.dev2022021300.dist-info/METADATA
utils_lib-0.2.0.dev2022021300.dist-info/WHEEL
utils_lib-0.2.0.dev2022021300.dist-info/top_level.txt
utils_lib-0.2.0.dev2022021300.dist-info/RECORD
