Metadata-Version: 2.1
Name: utils-lib
Version: 0.2.0.dev2022021300
Summary: Collection of general utilies
Home-page: https://github.com/jason40418/utils-lib-python
Author: Jason Lin
Author-email: jason40418@gmail.com
License: BSD-2-Clause
Keywords: utils-lib,utilities
Platform: UNKNOWN
Classifier: Development Status :: 1 - Planning
Classifier: License :: OSI Approved :: BSD License
Classifier: Programming Language :: Python :: 3
Classifier: Programming Language :: Python :: 3 :: Only
Classifier: Programming Language :: Python :: 3.6
Classifier: Programming Language :: Python :: 3.7
Classifier: Programming Language :: Python :: 3.8
Classifier: Programming Language :: Python :: 3.9
Classifier: Programming Language :: Python :: 3.10
Requires-Python: !=3.0.*,!=3.1.*,!=3.2.*,!=3.3.*,>=3.6
License-File: LICENSE
